[{"title": "Image note", "updated": "2016-08-14 23:50:16", "guid": "755a8f8e-7bbc-4e23-a914-c200ee6362e6", "created": "2016-08-14 18:20:22"}, {"title": "note with files", "updated": "2016-08-13 00:16:31", "guid": "8504594f-8a61-4968-a935-451059f51cf0", "created": "2016-08-13 00:16:31"}, {"title": "photo note", "updated": "2016-08-13 00:10:05", "guid": "8c262848-f640-492a-a87d-51a3609972d3", "created": "2016-08-13 00:10:05"}, {"title": "image note", "updated": "2016-08-13 00:07:28", "guid": "9ac6e8ea-e60d-49e2-8340-dc31143e260c", "created": "2016-08-13 00:07:28"}, {"title": "test note for editing", "updated": "2016-08-12 23:57:43", "guid": "91423699-ab4f-4181-82d8-5023d6b29a29", "created": "2016-08-12 23:57:43"}, {"title": "test note", "updated": "2016-08-11 01:16:14", "guid": "750c02ba-937d-401c-8056-caf0ecd05276", "created": "2016-08-11 00:10:26"}, {"title": "Test note for editng", "updated": "2016-08-10 22:33:14", "guid": "135fdc9f-04d5-4bea-9ff2-5ac71cc0dbf4", "created": "2016-08-09 22:41:30"}, {"title": "pdf note for editing", "updated": "2016-08-07 22:37:41", "guid": "cd653232-2fa9-4b00-85f5-be01e57d2f97", "created": "2016-08-07 13:35:10"}, {"title": "Image note 3", "updated": "2016-08-07 15:34:28", "guid": "d4be1dea-869f-4be5-acdb-9136ade48d11", "created": "2016-08-07 15:34:28"}, {"title": "Image note 2", "updated": "2016-08-07 15:24:18", "guid": "9c473367-8d61-4505-a658-834d27be7f07", "created": "2016-08-07 15:24:18"}, {"title": "Image note", "updated": "2016-08-07 15:21:32", "guid": "69e4892b-845c-4a8a-9366-08972c7c0801", "created": "2016-08-07 15:21:32"}, {"title": "pdf note for editing", "updated": "2016-08-07 13:35:10", "guid": "d70fab0e-f1d2-4bbc-b8a3-f726454d03a4", "created": "2016-08-07 13:35:10"}, {"title": "shared doc file", "updated": "2016-08-07 00:25:21", "guid": "d69376d8-9fd2-485a-ae7b-8e5008cc934c", "created": "2016-02-21 06:46:38"}, {"title": "shared Excel file", "updated": "2016-08-06 19:15:44", "guid": "9b80b4f7-529d-413c-b622-cd2d2ff80d68", "created": "2016-02-21 08:21:16"}, {"title": "Shared Word File", "updated": "2016-08-05 02:01:59", "guid": "d047c87b-b843-49c1-8520-99c69e12389d", "created": "2016-02-10 17:25:08"}, {"title": "Test note for editing", "updated": "2016-08-05 01:56:42", "guid": "21cc4761-c90d-4cef-a97e-0bb2d0f7e170", "created": "2016-08-03 01:09:04"}, {"title": "yes future", "updated": "2016-06-18 00:48:15", "guid": "77766091-1618-4098-a70d-e343f4263aab", "created": "2016-06-18 00:48:15"}, {"title": "test note", "updated": "2016-05-23 01:56:44", "guid": "47e2e6c5-bc43-4c3a-ad4f-ac0b71ee83e8", "created": "2016-05-23 01:56:44"}, {"title": "Shared doc file", "updated": "2016-02-13 15:18:36", "guid": "4b0d5b5b-fb52-4c1e-8492-d00d7aa1bbce", "created": "2016-02-13 15:18:36"}, {"title": "shared doc fike", "updated": "2016-02-12 17:45:09", "guid": "1239aa87-769d-4c18-a10a-1aefafcd18f6", "created": "2016-02-12 17:45:09"}, {"title": "Shared WPS fike", "updated": "2016-02-11 17:45:42", "guid": "8f21b572-1511-41b0-88dc-16cdead33ea6", "created": "2016-02-11 17:45:42"}, {"title": "Shared multiple files", "updated": "2016-02-11 17:17:26", "guid": "6623f529-3310-44c0-9042-07a71381b829", "created": "2016-02-11 17:17:26"}, {"title": "shared excel file", "updated": "2016-02-11 17:14:39", "guid": "01629bb2-6922-4365-80bb-e2c23325a98c", "created": "2016-02-11 17:14:39"}, {"title": "shared doc file", "updated": "2016-02-11 17:12:43", "guid": "aed775f5-c6c2-41fe-b88d-7d73a0ae3edf", "created": "2016-02-11 17:12:43"}, {"title": "Shared Images", "updated": "2016-02-10 17:37:52", "guid": "d07907a3-2f49-4ad7-9212-e14035a9c5ad", "created": "2016-02-10 17:37:52"}, {"title": "Shared PDF File", "updated": "2016-02-10 16:29:25", "guid": "d05d5d86-568d-4093-a76f-9ee13b79e98d", "created": "2016-02-10 16:29:25"}, {"title": "shared presentation", "updated": "2016-02-10 14:58:51", "guid": "c6987a38-3c17-4c67-b10b-d8bbc3f0f3b4", "created": "2016-02-10 14:58:51"}, {"title": "pdf note", "updated": "2016-02-09 17:36:48", "guid": "23a8720b-f7f4-4915-8bdc-b85f0f2dd35c", "created": "2016-02-09 17:36:48"}]